confusables/__init__.py
confusables/config.py
confusables/parse.py
confusables/utils.py
confusables/assets/confusable_mapping.json
confusables/assets/confusables.txt
confusables/assets/custom_confusables.txt
tests/__init__.py
tests/confusables/__init__.py
tests/confusables/test_confusables.py
confusables-1.2.0.dist-info/LICENSE
confusables-1.2.0.dist-info/METADATA
confusables-1.2.0.dist-info/WHEEL
confusables-1.2.0.dist-info/top_level.txt
confusables-1.2.0.dist-info/RECORD
