Metadata-Version: 2.1
Name: confusables
Version: 1.2.0
Summary: A python package providing functionality for matching words that can be confused for eachother, but contain different characters
Home-page: https://github.com/woodgern/confusables
Author: Nathan Woodger
Author-email: woodgern@gmail.com
License: UNKNOWN
Platform: UNKNOWN
Classifier: Programming Language :: Python :: 3
Classifier: License :: OSI Approved :: MIT License
Classifier: Operating System :: OS Independent
